<?xml version="1.0" encoding="utf-8"?>
<news>
  <title>Видеопросмотры, обсуждения Учения и медитации в Центре Ламы Цонкапы</title>
  <publish_date>2010-08-12</publish_date>
  <buddha_node>191</buddha_node>
  <body>
15 августа в Центре Ламы Цонкапы начинаются видеопросмотры и обсуждения
Учения, дарованных Досточтимым Геше Джампа Тинлеем в ходе прошедшего
этим летом ретрита на Байкале по II тому Ламрима. Начиная с сентября
просмотры и обсуждения будут чередоваться с медитациями на темы
Ламрима. +
 Занятия будут проходить по воскресеньям с 10-00 до 12-00 и с 13-00 до
15-00, и по средам с 19-00 до 21-00.
  </body>
</news>
