<?xml version="1.0" encoding="utf-8"?>
<teachings>
  <title>Осенние учения</title>
  <theme>
    <title>
      Комментарий к шаматхе, основанный на &#171;Среднем Ламриме&#187;
      Чже Цонкапы. Часть 3/3
    </title>
    <record>
      <description>
        Сущность буддизма.
      </description>
      <record_date>2017-11-09</record_date>
      <audio_url>2017-11-09_N01_GJT_Shamatha_Moscow_128.mp3</audio_url>
      <audio_size>94</audio_size>
      <youtube_id>6Cyi77ygvf0</youtube_id>
      <video_url/>
    </record>
    <record>
      <description>
        Определение блуждания и притупленности ума. Какую нужно развить
        бдительность. Общие причины блуждания и притупленности.
      </description>
      <record_date>2017-11-13</record_date>
      <audio_url>2017-11-13_N02_GJT_Shamatha_Moscow_128.mp3</audio_url>
      <audio_size>101</audio_size>
      <youtube_id>qN-CJo04oWA</youtube_id>
    </record>
    <record>
      <description>
        Cпецифические причины притупленности и блуждания. Косвенные
        противоядия от притупленности и блуждания. Что делать когда
        не возникает ошибок медитации.
      </description>
      <audio_url>2017-11-20_N03_GJT_Shamatha_Moscow_128.mp3</audio_url>
      <audio_size>98</audio_size>
      <record_date>2017-11-20</record_date>
      <youtube_id>Qi-_MHX5m1g</youtube_id>
    </record>
    <record>
      <description>
        Как развивать шаматху c распознанием 5&#160;ошибок медитации
        и применением 8&#160;противоядий. Как развить 9 стадий
        сосредоточения: стадии&#160;1&#160;-&#160;3.
      </description>
      <record_date>2017-11-23</record_date>
      <audio_url>2017-11-23_N04_GJT_Shamatha_Moscow_128.mp3</audio_url>
      <audio_size>87</audio_size>
      <youtube_id>6-hA5BmJuZk</youtube_id>
    </record>
    <record>
      <description>
        Как развить 9 стадий сосредоточения. Как достичь 9&#8209;ти
        стадий с помощью 6&#8209;ти сил.
      </description>
      <record_date>2017-11-27</record_date>
      <audio_url>2017-11-27_N05_GJT_Shamatha_Moscow_128.mp3</audio_url>
      <audio_size>97</audio_size>
      <youtube_id>YgJg-HpQMrU</youtube_id>
    </record>
    <record>
      <description>
        Общее учение в обзоре 3 уровней духовных личностей. 4 способа
        вступления в медитацию. Связь 9&#8209;ти стадий, 6&#8209;ти сил
        и 4&#8209;х способов вступления в медитацию.
      </description>
      <record_date>2017-11-30</record_date>
      <audio_url>2017-11-30_N06_GJT_Shamatha_Moscow_128.mp3</audio_url>
      <audio_size>104</audio_size>
      <youtube_id>JijVxV_B0Jc</youtube_id>
    </record>
    <record>
      <description>
	Мотивация личности среднего уровня. Критерий достижения шаматхи.
	Последовательность развития сосредоточния при медитации на ум.
      </description>
      <record_date>2017-12-04</record_date>
      <youtube_id>ZXmlpUCChO4</youtube_id>
    </record>
  </theme>
  <theme>
    <title>Комментарий к необычной Гуру-йоге</title>
    <record>
      <description>
        4 Мотивации развития Шаматхи. Как получать посвящение:
        предварительное посвящение, основное посвящение сосуда ученика
        (посвящение 5 Дхьяни-Будд/5 совокупностей).
      </description>
      <audio_url>2017-11-11_N01_GJT_Posvyashenie_Moscow_128.mp3</audio_url>
      <audio_size>99</audio_size>
      <record_date>2017-11-11</record_date>
      <youtube_id>BH3Lb9--JPg</youtube_id>
      <video_url/>
    </record>
    <record>
      <description>
        Важность изучения Дхармы. 4 печати буддизма. Различие между
        жентонг и рантонг.
      </description>
      <record_date>2017-11-25</record_date>
      <audio_url>2017-11-25_N02_GJT_4_pechati_128.mp3</audio_url>
      <audio_size>109</audio_size>
      <youtube_id>X-Ahi4fSw-s</youtube_id>
    </record>
    <record>
      <description>
        Соблюдение баланса практики и мирской деятельности. Правильный
        духовный дебют. 3 основых аспекта пути. Как сделать ума более
        здоровым через изучение философии.
      </description>
      <record_date>2017-12-02</record_date>
      <audio_url>2017-12-02_N03_GJT_kak_praktikovat_dharmu_128.mp3</audio_url>
      <audio_size>96</audio_size>
      <youtube_id>qJVRdlWlbIA</youtube_id>
    </record>
  </theme>
</teachings>
